kupo/__init__.py
kupo/app.py
kupo/kupo.css
kupo/kupo_commands.md
kupo-0.1.0a0.dist-info/entry_points.txt
kupo-0.1.0a0.dist-info/WHEEL
kupo-0.1.0a0.dist-info/METADATA
kupo-0.1.0a0.dist-info/RECORD
